[
  {
    "type": "stack",
    "up": [
      {
        "id": "tripple_corpus",
        "slots": [
            ["corpus"],
            ["corpus"],
            ["corpus"]
        ],
        "reagents": [1],
        "duration": 10,
        "style": 2
      },
      {
        "id": "dread_remover",
        "slots": [
            ["dread"],
            ["dread"]
        ],
        "reagents": [1, 2],
        "duration": 10,
        "style": 1
      },
      {
        "id": "corpus_up",
        "slots": [
            ["corpus"],
            ["corpus"]
        ],
        "reagents": [1],
        "output_success": { "inventory": { "root": ["fatigue"] } },
        "duration": 10,
        "style": 2
      },
      {
        "id": "woodcutting",
        "slots": [
            [["labor", 1], [], ["wood", 1]],
            ["corpus"]
        ],
        "reagents": [1],
        "output_success": {
          "inventory": {
            "root": ["fatigue"],
            "actor": [["log", [4, 1], "vigor"]]
          }
        },
        "duration": 30,
        "style": 1
      }
    ],
    "down": [
      {
        "id": "corpus_down_aspect",
        "slots": [
            ["corpus", 1],
            ["corpus"]
        ],
        "reagents": [1],
        "duration": 10,
        "style": 2
      },
      {
        "id": "corpus_down",
        "slots": [
            ["corpus"],
            ["corpus"]
        ],
        "reagents": [1],
        "output_success": { "inventory": { "root": ["corpus"] } },
        "duration": 10,
        "style": 2
      }
    ]
  },
  {
    "type": "on_create",
    "self": [
      {
        "id": "fatigue",
        "root": ["fatigue"],
        "reagents": ["root"],
        "output_success": { "inventory": { "actor": ["corpus"] } },
        "duration": 30,
        "style": 2
      },
      {
        "id": "fleeting",
        "root": [["fleeting", 1]],
        "reagents": ["root"],
        "duration": 
        [
            [20, [["fleeting", 4]]],
            [15, [["fleeting", 3]]],
            [10, [["fleeting", 2]]],
            5
        ],
        "style": 2
      }
    ],
    "magnetic": [
      {
        "id": "despair",
        "hex": ["despair"],
        "set_start": { 
          "hex": {"drop_locked": true, "surface_locked": true} 
        },
        "magnetic_success": "magnetic.up.despair_success",
        "magnetic_failure": "magnetic.up.despair_failure",
        "duration": 60,
        "delay": 10,
        "interval": 2,
        "style": 1
      }
    ]
  },
  {
    "type": "magnetic",
    "up": [
      {
        "id": "despair_success",
        "hex": ["despair"],
        "root": ["dread"],
        "reagents": ["hex", "root"],
        "set_start": {
          "root": {"drop_hold": true, "position_hold": true} 
        },
        "output_success": { "inventory": { "hex": ["corpus"] } },
        "duration": 10,
        "style": 1
      },
      {
        "id": "despair_failure",
        "hex": ["despair"],
        "reagents": ["hex"],
        "set_start": {},
        "output_success": { "inventory": { "hex": ["dread"] } },
        "duration": 10,
        "style": 1
      }
    ],
    "down": [
      
    ]
  }
]
